cruntils/__init__.py
cruntils/__main__.py
cruntils/artifactory.py
cruntils/database.py
cruntils/docker.py
cruntils/docker_hub.py
cruntils/fw.py
cruntils/gis.py
cruntils/obj.py
cruntils/print.py
cruntils/psutils.py
cruntils/serial.py
cruntils/utils.py
cruntils/windows/__init__.py
cruntils/windows/_mapped_network_drives.py
cruntils/windows/services.py
cruntils-1.5.0.dist-info/licenses/LICENSE
cruntils-1.5.0.dist-info/METADATA
cruntils-1.5.0.dist-info/WHEEL
cruntils-1.5.0.dist-info/top_level.txt
cruntils-1.5.0.dist-info/RECORD
