Metadata-Version: 2.4
Name: cruntils
Version: 1.5.0
Summary: A collection of utilities.
Author: CReed
Requires-Python: >=3.7
License-File: LICENSE
Requires-Dist: pyserial>=3.5
Requires-Dist: requests>=2.32.5
Provides-Extra: windows
Requires-Dist: pywin32>=306; extra == "windows"
Dynamic: license-file
